Code/24withEN/24.v
// Initialize verilog module, stating input and output will be used
module decoder_24(
	input [1:0]w,
	input EN,
	output [3:0]out
);

// Stating behavioral model, output 'out' is stated by 'reg'
// The output is always preserved by the input 'w'
reg [3:0]out;
always @(w,EN)
begin
	if(EN==1'b1) //When Enable
		if (w==2'b00)
		out=4'b0001;
		else if (w==2'b01)
    	    out=4'b0010;
		else if (w==2'b10)
    	    out=4'b0100;
		else if (w==2'b11)
    	    out=4'b1000;
		else
    	    out=4'bZZZZ; // for rare situation
	else // When disable, output=0
	out=4'b0000;
end
endmodule

Code/24withEN/tb_decoder_24.v
// Simulating baseline time for simulation control
`timescale 1ns / 1ns

// Initialize module for test bench
module tb_decoder_24;
// Input circuit 2bit
reg [1:0]w;
reg EN;

// Output circuit
wire [3:0]out;

// Instantiate  
decoder_24 decoder1 (w, EN, out);

//Initialize begin
initial begin
	// Create file 'vcd' for running on gtkwave while compiling
	$dumpfile ("tb.vcd");
	$dumpvars (0, tb_decoder_24);
       #0 w = 2'b00;  EN=1'b0 ;
       #10 w = 2'b01; EN=1'b0;
       #10 w = 2'b10; EN=1'b0;
       #10 w = 2'b11; EN=1'b0;
	   #10 w = 2'b00; EN=1'b1;
       #10 w = 2'b01; EN=1'b1;
       #10 w = 2'b10; EN=1'b1;
       #10 w = 2'b11; EN=1'b1;
	   #10 ;
	
end
endmodule

Code/24withEN/tb.vcd
$date
	Wed Nov 11 20:30:54 2020
$end
$version
	Icarus Verilog
$end
$timescale
	1ns
$end
$scope module tb_decoder_24 $end
$var wire 4 ! out [3:0] $end
$var reg 1 " EN $end
$var reg 2 # w [1:0] $end
$scope module decoder1 $end
$var wire 1 " EN $end
$var wire 2 $ w [1:0] $end
$var reg 4 % out [3:0] $end
$upscope $end
$upscope $end
$enddefinitions $end
#0
$dumpvars
b0 %
b0 $
b0 #
0"
b0 !
$end
#10
b1 #
b1 $
#20
b10 #
b10 $
#30
b11 #
b11 $
#40
b1 !
b1 %
1"
b0 #
b0 $
#50
b10 !
b10 %
b1 #
b1 $
#60
b100 !
b100 %
b10 #
b10 $
#70
b1000 !
b1000 %
b11 #
b11 $
