Code/38decoder/decoder_24.v
// // Initialize verilog module, stating input and output will be used
// module decoder_24(
// 	input [1:0]w,
// 	input EN,
// 	output [3:0]out
// );

// // Stating behavioral model, output 'out' is stated by 'reg'
// // The output is always preserved by the input 'w'
// reg [3:0]out;
// always @(w)
// begin
// 	if(EN==1'b1)
// 		if (w==2'b00)
// 		out=4'b0001;
// 		else if (w==2'b01)
//     	    out=4'b0010;
// 		else if (w==2'b10)
//     	    out=4'b0100;
// 		else if (w==2'b11)
//     	    out=4'b1000;
// 		else
//     	    out=4'bZZZZ; // for rare situation
// 	else
// 	out=4'b0000;
// end
// endmodule


module decoder_24 (
       input [1:0]w,
       input EN,
       output [3:0]out
);

assign out[0] = ~w[1] &  ~w[0] & EN;
assign out[1] = ~w[1] &  w[0]  & EN;
assign out[2] = w[1]  &  ~w[0] & EN;
assign out[3] = w[1]  &  w[0]  & EN;

endmodule

Code/38decoder/decoder_38.v
module decoder_38 (
    input [2:0]w,
	output [7:0]out
);
 
 decoder_24 dec0 ( w[1:0], ~w[2],  out[3:0]);
 decoder_24 dec1 ( w[1:0], w[2] ,  out[7:4]);

endmodule

Code/38decoder/tb.v
`timescale 1ns / 1ns

module tb;

reg [2:0] w;
wire [7:0] out;

decoder_38 dec(w,out);
initial begin
    $dumpfile ("tb.vcd");
	$dumpvars (0, tb);
    w= 3'b000;
    #10 w= 3'b001;
    #10 w= 3'b010;
    #10 w= 3'b011;
    #10 w= 3'b100;
    #10 w= 3'b101;
    #10 w= 3'b110;
    #10 w= 3'b111;
    #20;
     
end
endmodule

Code/38decoder/tb.vcd
$date
	Wed Nov 11 20:45:51 2020
$end
$version
	Icarus Verilog
$end
$timescale
	1ns
$end
$scope module tb $end
$var wire 8 ! out [7:0] $end
$var reg 3 " w [2:0] $end
$scope module dec $end
$var wire 3 # w [2:0] $end
$var wire 8 $ out [7:0] $end
$scope module dec0 $end
$var wire 1 % EN $end
$var wire 2 & w [1:0] $end
$var wire 4 ' out [3:0] $end
$upscope $end
$scope module dec1 $end
$var wire 1 ( EN $end
$var wire 2 ) w [1:0] $end
$var wire 4 * out [3:0] $end
$upscope $end
$upscope $end
$upscope $end
$enddefinitions $end
#0
$dumpvars
b0 *
b0 )
0(
b1 '
b0 &
1%
b1 $
b0 #
b0 "
b1 !
$end
#10
b10 !
b10 $
b10 '
b1 &
b1 )
b1 "
b1 #
#20
b100 !
b100 $
b100 '
b10 &
b10 )
b10 "
b10 #
#30
b1000 !
b1000 $
b1000 '
b11 &
b11 )
b11 "
b11 #
#40
b0 '
0%
b10000 !
b10000 $
b1 *
b0 &
b0 )
1(
b100 "
b100 #
#50
b100000 !
b100000 $
b10 *
b1 &
b1 )
b101 "
b101 #
#60
b1000000 !
b1000000 $
b100 *
b10 &
b10 )
b110 "
b110 #
#70
b10000000 !
b10000000 $
b1000 *
b11 &
b11 )
b111 "
b111 #
